django_jenkins/__init__.py
django_jenkins/apps.py
django_jenkins/models.py
django_jenkins/runner.py
django_jenkins/management/__init__.py
django_jenkins/management/commands/__init__.py
django_jenkins/management/commands/jenkins.py
django_jenkins/tasks/__init__.py
django_jenkins/tasks/pylint.rc
django_jenkins/tasks/run_flake8.py
django_jenkins/tasks/run_pep8.py
django_jenkins/tasks/run_pyflakes.py
django_jenkins/tasks/run_pylint.py
django_jenkins/tasks/with_coverage.py
django4_jenkins-1.0.0.dist-info/LICENSE
django4_jenkins-1.0.0.dist-info/METADATA
django4_jenkins-1.0.0.dist-info/WHEEL
django4_jenkins-1.0.0.dist-info/top_level.txt
django4_jenkins-1.0.0.dist-info/RECORD
